lazydict.py
setup.py
lazydict.egg-info/PKG-INFO
lazydict.egg-info/SOURCES.txt
lazydict.egg-info/dependency_links.txt
lazydict.egg-info/top_level.txt