Metadata-Version: 1.1
Name: lazydict
Version: 1.0.0b2
Summary: Lazily-evaluated dictionaries
Home-page: https://github.com/janrain/lazydict
Author: Colin von Heuring
Author-email: colin@von.heuri.ng
License: MIT License
Download-URL: https://pypi.python.org/packages/source/l/lazydict/lazydict-1.0.0-beta.2.tar.gz
Platform: any
Classifier: Development Status :: 4 - Beta
Classifier: Intended Audience :: Developers
Classifier: License :: OSI Approved :: MIT License
Classifier: Programming Language :: Python
Classifier: Topic :: Software Development :: Libraries :: Python Modules
Classifier: Operating System :: OS Independent
